__init__.py
cehrbert_data/__init__.py
cehrbert_data/apps/__init__.py
cehrbert_data/apps/generate_included_concept_list.py
cehrbert_data/apps/generate_training_data.py
cehrbert_data/cohorts/__init__.py
cehrbert_data/cohorts/atrial_fibrillation.py
cehrbert_data/cohorts/cabg.py
cehrbert_data/cohorts/coronary_artery_disease.py
cehrbert_data/cohorts/covid.py
cehrbert_data/cohorts/covid_inpatient.py
cehrbert_data/cohorts/death.py
cehrbert_data/cohorts/heart_failure.py
cehrbert_data/cohorts/ischemic_stroke.py
cehrbert_data/cohorts/last_visit_discharged_home.py
cehrbert_data/cohorts/query_builder.py
cehrbert_data/cohorts/spark_app_base.py
cehrbert_data/cohorts/type_two_diabietes.py
cehrbert_data/cohorts/ventilation.py
cehrbert_data/config/__init__.py
cehrbert_data/config/output_names.py
cehrbert_data/const/__init__.py
cehrbert_data/const/artificial_tokens.py
cehrbert_data/const/common.py
cehrbert_data/const/__pycache__/__init__.cpython-311.pyc
cehrbert_data/const/__pycache__/common.cpython-311.pyc
cehrbert_data/decorators/__init__.py
cehrbert_data/decorators/artificial_time_token_decorator.py
cehrbert_data/decorators/clinical_event_decorator.py
cehrbert_data/decorators/death_event_decorator.py
cehrbert_data/decorators/demographic_event_decorator.py
cehrbert_data/decorators/patient_event_decorator_base.py
cehrbert_data/decorators/prediction_token_decorator.py
cehrbert_data/decorators/token_priority.py
cehrbert_data/prediction_cohorts/__init__.py
cehrbert_data/prediction_cohorts/afib_ischemic_stroke.py
cehrbert_data/prediction_cohorts/cad_cabg_cohort.py
cehrbert_data/prediction_cohorts/cad_hf_cohort.py
cehrbert_data/prediction_cohorts/copd_readmission.py
cehrbert_data/prediction_cohorts/covid_death.py
cehrbert_data/prediction_cohorts/covid_ventilation.py
cehrbert_data/prediction_cohorts/discharge_home_death.py
cehrbert_data/prediction_cohorts/hf_readmission.py
cehrbert_data/prediction_cohorts/hospitalization.py
cehrbert_data/prediction_cohorts/hospitalization_mortality.py
cehrbert_data-0.1.1.dist-info/licenses/LICENSE
cehrbert_data-0.1.1.dist-info/METADATA
cehrbert_data-0.1.1.dist-info/WHEEL
cehrbert_data-0.1.1.dist-info/top_level.txt
cehrbert_data-0.1.1.dist-info/RECORD
