Metadata-Version: 2.4
Name: cehrbert_data
Version: 0.1.1
Summary: The Spark ETL tools for generating the CEHR-BERT and CEHR-GPT pre-training and finetuning data
Author-email: Chao Pang <chaopang229@gmail.com>, Xinzhuo Jiang <xj2193@cumc.columbia.edu>, Krishna Kalluri <kk3326@cumc.columbia.edu>, Nishanth Parameshwar Pavinkurve <np2689@cumc.columbia.edu>, Karthik Natarajan <kn2174@cumc.columbia.edu>
License: MIT License
Project-URL: Homepage, https://github.com/knatarajan-lab/cehrbert_data
Classifier: Development Status :: 5 - Production/Stable
Classifier: Intended Audience :: Developers
Classifier: Intended Audience :: Science/Research
Classifier: License :: OSI Approved :: MIT License
Classifier: Programming Language :: Python :: 3
Requires-Python: >=3.10.0
License-File: LICENSE
Requires-Dist: numpy>=1.24.3
Requires-Dist: packaging>=23.2
Requires-Dist: pandas>=2.2.0
Requires-Dist: pyspark==3.1.2
Provides-Extra: dev
Requires-Dist: pre-commit; extra == "dev"
Requires-Dist: pytest; extra == "dev"
Requires-Dist: pytest-cov; extra == "dev"
Requires-Dist: pytest-subtests; extra == "dev"
Requires-Dist: rootutils; extra == "dev"
Requires-Dist: hypothesis; extra == "dev"
Requires-Dist: black; extra == "dev"
Dynamic: license-file
